LICENCE.txt
MANIFEST.in
README.rst
setup.cfg
setup.py
sveetoy_cli/__init__.py
sveetoy_cli/export.py
sveetoy_cli/logs.py
sveetoy_cli/schemes.py
sveetoy_cli.egg-info/PKG-INFO
sveetoy_cli.egg-info/SOURCES.txt
sveetoy_cli.egg-info/dependency_links.txt
sveetoy_cli.egg-info/entry_points.txt
sveetoy_cli.egg-info/not-zip-safe
sveetoy_cli.egg-info/requires.txt
sveetoy_cli.egg-info/top_level.txt
sveetoy_cli/cli/__init__.py
sveetoy_cli/cli/colors.py
sveetoy_cli/cli/console_script.py
sveetoy_cli/cli/export.py
sveetoy_cli/cli/schemes.py
sveetoy_cli/cli/version.py
sveetoy_cli/colors/__init__.py
sveetoy_cli/colors/dumper.py
sveetoy_cli/colors/finder.py
sveetoy_cli/colors/naming.py
sveetoy_cli/colors/registry.py