Metadata-Version: 1.1
Name: sveetoy-cli
Version: 0.3.0
Summary: Commandline tools around Sveetoy Sass library
Home-page: https://github.com/sveetch/sveetoy-cli
Author: David Thenon
Author-email: sveetch@gmail.com
License: MIT
Platform: UNKNOWN
Classifier: Development Status :: 3 - Alpha
Classifier: Environment :: Console
Classifier: Intended Audience :: Developers
Classifier: License :: OSI Approved :: MIT License
Classifier: Operating System :: OS Independent
Classifier: Programming Language :: Python
Classifier: Programming Language :: Python :: 3.5
Classifier: Topic :: Internet
Classifier: Topic :: Software Development :: Libraries :: Python Modules
